<?xml version="1.0" encoding="UTF-8"?>
<Scheme
   LastUpgradeVersion = "0710"
   version = "1.3">
   <BuildAction
      parallelizeBuildables = "YES"
      buildImplicitDependencies = "YES">
      <BuildActionEntries>
         <BuildActionEntry
            buildForTesting = "YES"
            buildForRunning = "YES"
            buildForProfiling = "YES"
            buildForArchiving = "YES"
            buildForAnalyzing = "YES">
            <BuildableReference
               BuildableIdentifier = "primary"
               BlueprintIdentifier = "5E1352351FD990D500650046"
               BuildableName = "msched"
               BlueprintName = "msched"
               ReferencedContainer = "container:msched.xcodeproj">
            </BuildableReference>
         </BuildActionEntry>
      </BuildActionEntries>
   </BuildAction>
   <TestAction
      buildConfiguration = "Debug"
      selectedDebuggerIdentifier = "Xcode.DebuggerFoundation.Debugger.LLDB"
      selectedLauncherIdentifier = "Xcode.DebuggerFoundation.Launcher.LLDB"
      shouldUseLaunchSchemeArgsEnv = "YES">
      <Testables>
      </Testables>
      <MacroExpansion>
         <BuildableReference
            BuildableIdentifier = "primary"
            BlueprintIdentifier = "5E1352351FD990D500650046"
            BuildableName = "msched"
            BlueprintName = "msched"
            ReferencedContainer = "container:msched.xcodeproj">
         </BuildableReference>
      </MacroExpansion>
      <AdditionalOptions>
      </AdditionalOptions>
   </TestAction>
   <LaunchAction
      buildConfiguration = "Debug"
      selectedDebuggerIdentifier = "Xcode.DebuggerFoundation.Debugger.LLDB"
      selectedLauncherIdentifier = "Xcode.DebuggerFoundation.Launcher.LLDB"
      launchStyle = "0"
      useCustomWorkingDirectory = "YES"
      customWorkingDirectory = "/Users/zy/Desktop/USACO/msched/msched"
      ignoresPersistentStateOnLaunch = "NO"
      debugDocumentVersioning = "YES"
      debugServiceExtension = "internal"
      allowLocationSimulation = "YES">
      <BuildableProductRunnable
         runnableDebuggingMode = "0">
         <BuildableReference
            BuildableIdentifier = "primary"
            BlueprintIdentifier = "5E1352351FD990D500650046"
            BuildableName = "msched"
            BlueprintName = "msched"
            ReferencedContainer = "container:msched.xcodeproj">
         </BuildableReference>
      </BuildableProductRunnable>
      <AdditionalOptions>
      </AdditionalOptions>
   </LaunchAction>
   <ProfileAction
      buildConfiguration = "Release"
      shouldUseLaunchSchemeArgsEnv = "YES"
      savedToolIdentifier = ""
      useCustomWorkingDirectory = "NO"
      debugDocumentVersioning = "YES">
      <BuildableProductRunnable
         runnableDebuggingMode = "0">
         <BuildableReference
            BuildableIdentifier = "primary"
            BlueprintIdentifier = "5E1352351FD990D500650046"
            BuildableName = "msched"
            BlueprintName = "msched"
            ReferencedContainer = "container:msched.xcodeproj">
         </BuildableReference>
      </BuildableProductRunnable>
   </ProfileAction>
   <AnalyzeAction
      buildConfiguration = "Debug">
   </AnalyzeAction>
   <ArchiveAction
      buildConfiguration = "Release"
      revealArchiveInOrganizer = "YES">
   </ArchiveAction>
</Scheme>
